modal_mcp_toolbox/__init__.py
modal_mcp_toolbox/__main__.py
modal_mcp_toolbox/code.py
modal_mcp_toolbox/flux.py
modal_mcp_toolbox-0.1.12.dist-info/METADATA
modal_mcp_toolbox-0.1.12.dist-info/WHEEL
modal_mcp_toolbox-0.1.12.dist-info/entry_points.txt
modal_mcp_toolbox-0.1.12.dist-info/licenses/LICENSE
modal_mcp_toolbox-0.1.12.dist-info/RECORD
