Metadata-Version: 2.4
Name: modal-mcp-toolbox
Version: 0.1.12
Summary: A collection of Model Context Protocol (MCP) tools for Modal
Author-email: Philipp Eisen <hello@philippeisen.de>
License-File: LICENSE
Requires-Python: <3.13,>=3.10
Requires-Dist: mcp>=1.3.0
Requires-Dist: modal>=0.73.43
